{
  "kind": "collectionType",
  "collectionName": "posts",
  "info": {
    "name": "Post",
    "description": ""
  },
  "options": {
    "increments": true,
    "timestamps": true,
    "draftAndPublish": true
  },
  "pluginOptions": {},
  "attributes": {
    "title": {
      "type": "string"
    },
    "content": {
      "type": "richtext"
    },
    "excerpt": {
      "type": "string"
    },
    "slug": {
      "type": "uid",
      "targetField": "title"
    },
    "pinned": {
      "type": "boolean",
      "default": false
    }
  }
}
